classical/__init__.py
classical/descriptors.py
classical/subclass.py
classical/fields/__init__.py
classical/fields/attrs.py
classical/fields/base.py
classical/fields/dataclass.py
classical/fields/dict.py
classical/fields/functions.py
classical/fields/generic.py
classical/fields/namedtuple.py
classical/fields/schematics.py
classical/fields/sqlalchemy.py
classical-2.1.2.dist-info/LICENSE
classical-2.1.2.dist-info/METADATA
classical-2.1.2.dist-info/WHEEL
classical-2.1.2.dist-info/top_level.txt
classical-2.1.2.dist-info/RECORD
