Metadata-Version: 2.1
Name: classical
Version: 2.1.2
Summary: Class Tools for Python
Home-page: https://github.com/altvod/classical
Author: Grigory Statsenko
License: MIT
Keywords: class,utilities,descriptors,properties,factories,dataclasses,attrs,fields,schematics,sqlalchemy
Platform: UNKNOWN
Classifier: Development Status :: 4 - Beta
Classifier: Intended Audience :: Developers
Classifier: Topic :: Software Development :: Libraries :: Python Modules
Classifier: License :: OSI Approved :: MIT License
Classifier: Programming Language :: Python :: 3 :: Only
Classifier: Programming Language :: Python :: 3
Classifier: Programming Language :: Python :: 3.5
Classifier: Programming Language :: Python :: 3.6
Classifier: Programming Language :: Python :: 3.7
Classifier: Programming Language :: Python :: 3.8
Classifier: Programming Language :: Python :: 3.9
Classifier: Programming Language :: Python :: 3.10
Provides-Extra: build
Requires-Dist: build ; extra == 'build'
Requires-Dist: twine ; extra == 'build'
Provides-Extra: docs
Requires-Dist: sphinx ; extra == 'docs'
Requires-Dist: sphinx-rtd-theme ; extra == 'docs'
Provides-Extra: fielded
Requires-Dist: attr ; extra == 'fielded'
Requires-Dist: schematics ; extra == 'fielded'
Requires-Dist: sqlalchemy ; extra == 'fielded'
Provides-Extra: testing
Requires-Dist: pylama ; extra == 'testing'
Requires-Dist: pytest ; extra == 'testing'
Requires-Dist: pytest-cov ; extra == 'testing'
Requires-Dist: pytest-html ; extra == 'testing'
